shipyard_fivetran/__init__.py
shipyard_fivetran/cli/__init__.py
shipyard_fivetran/cli/authtest.py
shipyard_fivetran/cli/sync.py
shipyard_fivetran/cli/update_connector.py
shipyard_fivetran/fivetran.py
shipyard_fivetran-0.2.1.dist-info/METADATA
shipyard_fivetran-0.2.1.dist-info/WHEEL
shipyard_fivetran-0.2.1.dist-info/RECORD
